[
    {
        "id": "3QO1",
        "booking": {
            "bookingName": "sdfghjkl",
            "bookingDateTime": "05/03/2024 11:55",
            "hotel": "ASDFGHJK",
            "contactPhone": "+998972832356",
            "room": "43"
        }
    },
    {
        "id": "L1qM",
        "booking": {
            "bookingName": "sdfghjkl",
            "bookingDateTime": "11/03/2024 12:24",
            "hotel": "ASDFGHJK",
            "contactPhone": "+998972832356",
            "room": "43"
        }
    }
]